{
  "unversionedId": "components/index",
  "id": "components/index",
  "title": "Components",
  "description": "Let's say something about components here.",
  "source": "@site/docs/components/index.md",
  "sourceDirName": "components",
  "slug": "/components/",
  "permalink": "/docs/components/",
  "draft": false,
  "editUrl": "https://github.com/SFDigitalServices/design-system/tree/main/docs/components/index.md",
  "tags": [],
  "version": "current",
  "frontMatter": {
    "title": "Components"
  },
  "sidebar": "componentsSidebar",
  "previous": {
    "title": "Fields and Forms",
    "permalink": "/docs/components/fields-and-forms"
  },
  "next": {
    "title": "Component Stuffs",
    "permalink": "/docs/components/intro"
  }
}